setup.py
akash_iq_library/__init__.py
akash_iq_library/akash_iq_library.py
akash_iq_library.egg-info/PKG-INFO
akash_iq_library.egg-info/SOURCES.txt
akash_iq_library.egg-info/dependency_links.txt
akash_iq_library.egg-info/not-zip-safe
akash_iq_library.egg-info/top_level.txt