Metadata-Version: 2.1
Name: akash-iq-library
Version: 0.1
Summary: contains many data science modules
Home-page: UNKNOWN
Author: Akash Kumar
License: UNKNOWN
Platform: UNKNOWN
